sentry_sprintly
