Metadata-Version: 1.0
Name: sentry-sprintly
Version: 0.1.3
Summary: A Sentry extension which integrates with Sprint.ly
Home-page: http://github.com/mattrobenolt/sentry-sprintly
Author: Matt Robenolt
Author-email: matt@ydekproductons.com
License: BSD
Platform: UNKNOWN
Classifier: Framework :: Django
Classifier: Intended Audience :: Developers
Classifier: Intended Audience :: System Administrators
Classifier: Operating System :: OS Independent
Classifier: Topic :: Software Development
